py_client/__init__.py
py_client/client.py
py_client/DBM/__init__.py
py_client/DBM/dbm_ice.py
py_client/Demo/FDFS_ice.py
py_client/Demo/__init__.py
amberai_ice_rpc-1.0.3.dist-info/LICENSE
amberai_ice_rpc-1.0.3.dist-info/METADATA
amberai_ice_rpc-1.0.3.dist-info/WHEEL
amberai_ice_rpc-1.0.3.dist-info/top_level.txt
amberai_ice_rpc-1.0.3.dist-info/RECORD
