Metadata-Version: 2.1
Name: amberai-ice-rpc
Version: 1.0.3
Summary: AMBER AI group dedicated RPC framwork call sdk base rp
Home-page: UNKNOWN
Author: chn1807
Author-email: chn1807@163.com
Maintainer: chn1807
Maintainer-email: chn1807@163.com
License: MIT
Keywords: amberai ice rpc
Platform: UNKNOWN
Requires-Dist: zeroc-ice (==3.7.1)
